MANIFEST.in
Makefile
README.md
setup.py
stclassify/__init__.py
stclassify/base.py
stclassify/classifier.py
stclassify/text_process.py
stclassify.egg-info/PKG-INFO
stclassify.egg-info/SOURCES.txt
stclassify.egg-info/dependency_links.txt
stclassify.egg-info/requires.txt
stclassify.egg-info/top_level.txt
stclassify/svc_impl/Makefile
stclassify/svc_impl/__init__.py
stclassify/svc_impl/learner_impl.py
stclassify/svc_impl/test.cpp
stclassify/svc_impl/util.c
stclassify/svc_impl/liblinear/Makefile
stclassify/svc_impl/liblinear/linear.cpp
stclassify/svc_impl/liblinear/linear.h
stclassify/svc_impl/liblinear/predict.c
stclassify/svc_impl/liblinear/train.c
stclassify/svc_impl/liblinear/tron.cpp
stclassify/svc_impl/liblinear/tron.h
stclassify/svc_impl/liblinear/blas/Makefile
stclassify/svc_impl/liblinear/blas/blas.h
stclassify/svc_impl/liblinear/blas/blasp.h
stclassify/svc_impl/liblinear/blas/daxpy.c
stclassify/svc_impl/liblinear/blas/ddot.c
stclassify/svc_impl/liblinear/blas/dnrm2.c
stclassify/svc_impl/liblinear/blas/dscal.c
stclassify/svc_impl/liblinear/python/Makefile
stclassify/svc_impl/liblinear/python/__init__.py
stclassify/svc_impl/liblinear/python/liblinear.py
stclassify/svc_impl/liblinear/python/liblinearutil.py