Metadata-Version: 2.1
Name: stclassify
Version: 0.1.0.22
Summary: short_text_classify
Home-page: https://github.com/wac81/short_text_classify
Author: wac
Author-email: wuanch@gmail.com
License: UNKNOWN
Platform: UNKNOWN
Classifier: Programming Language :: Python :: 3
Classifier: License :: OSI Approved :: MIT License
Classifier: Operating System :: OS Independent
